<?xml version="1.0" encoding="UTF-8" ?>
<OpenSimDocument Version="30000">
	<MarkerSet>
		<objects>
			<Marker name="FHD">
				<!--Body segment in the model on which the marker resides.-->
				<body>torso</body>
				<!--Location of a marker on the body segment.-->
				<location> 0.0927072 0.597103 -0.00414687</location>
				<!--Flag (true or false) specifying whether or not a marker should be kept fixed in the marker placement step.  i.e. If false, the marker is allowed to move.-->
				<fixed>true</fixed>
			</Marker>
			<Marker name="LBHD">
				<!--Body segment in the model on which the marker resides.-->
				<body>torso</body>
				<!--Location of a marker on the body segment.-->
				<location> -0.0849905 0.569706 -0.043139</location>
				<!--Flag (true or false) specifying whether or not a marker should be kept fixed in the marker placement step.  i.e. If false, the marker is allowed to move.-->
				<fixed>false</fixed>
			</Marker>
			<Marker name="RBHD">
				<!--Body segment in the model on which the marker resides.-->
				<body>torso</body>
				<!--Location of a marker on the body segment.-->
				<location> -0.0794098 0.571023 0.0515235</location>
				<!--Flag (true or false) specifying whether or not a marker should be kept fixed in the marker placement step.  i.e. If false, the marker is allowed to move.-->
				<fixed>false</fixed>
			</Marker>
			<Marker name="C7">
				<!--Body segment in the model on which the marker resides.-->
				<body>torso</body>
				<!--Location of a marker on the body segment.-->
				<location> -0.085 0.435 0.00165426</location>
				<!--Flag (true or false) specifying whether or not a marker should be kept fixed in the marker placement step.  i.e. If false, the marker is allowed to move.-->
				<fixed>true</fixed>
			</Marker>
			<Marker name="T10">
				<!--Body segment in the model on which the marker resides.-->
				<body>torso</body>
				<!--Location of a marker on the body segment.-->
				<location> -0.0943921 0.203142 -0.00142022</location>
				<!--Flag (true or false) specifying whether or not a marker should be kept fixed in the marker placement step.  i.e. If false, the marker is allowed to move.-->
				<fixed>false</fixed>
			</Marker>
			<Marker name="CLAV">
				<!--Body segment in the model on which the marker resides.-->
				<body>torso</body>
				<!--Location of a marker on the body segment.-->
				<location> 0.0486694 0.369107 0.00046003</location>
				<!--Flag (true or false) specifying whether or not a marker should be kept fixed in the marker placement step.  i.e. If false, the marker is allowed to move.-->
				<fixed>true</fixed>
			</Marker>
			<Marker name="LSHO">
				<!--Body segment in the model on which the marker resides.-->
				<body>torso</body>
				<!--Location of a marker on the body segment.-->
				<location> -0.00250296 0.422783 -0.149713</location>
				<!--Flag (true or false) specifying whether or not a marker should be kept fixed in the marker placement step.  i.e. If false, the marker is allowed to move.-->
				<fixed>true</fixed>
			</Marker>
			<Marker name="LUUPA">
				<!--Body segment in the model on which the marker resides.-->
				<body>humerus_l</body>
				<!--Location of a marker on the body segment.-->
				<location> 0.00294495 -0.136357 -0.0257785</location>
				<!--Flag (true or false) specifying whether or not a marker should be kept fixed in the marker placement step.  i.e. If false, the marker is allowed to move.-->
				<fixed>false</fixed>
			</Marker>
			<Marker name="LMUPA">
				<!--Body segment in the model on which the marker resides.-->
				<body>humerus_l</body>
				<!--Location of a marker on the body segment.-->
				<location> 0.0018115 -0.191504 -0.0185006</location>
				<!--Flag (true or false) specifying whether or not a marker should be kept fixed in the marker placement step.  i.e. If false, the marker is allowed to move.-->
				<fixed>false</fixed>
			</Marker>
			<Marker name="LDUPA">
				<!--Body segment in the model on which the marker resides.-->
				<body>humerus_l</body>
				<!--Location of a marker on the body segment.-->
				<location> 0.0282514 -0.163572 -0.0275973</location>
				<!--Flag (true or false) specifying whether or not a marker should be kept fixed in the marker placement step.  i.e. If false, the marker is allowed to move.-->
				<fixed>false</fixed>
			</Marker>
			<Marker name="LLEP">
				<!--Body segment in the model on which the marker resides.-->
				<body>humerus_l</body>
				<!--Location of a marker on the body segment.-->
				<location> 0.015 -0.28 -0.04</location>
				<!--Flag (true or false) specifying whether or not a marker should be kept fixed in the marker placement step.  i.e. If false, the marker is allowed to move.-->
				<fixed>true</fixed>
			</Marker>
			<Marker name="LMEP">
				<!--Body segment in the model on which the marker resides.-->
				<body>humerus_l</body>
				<!--Location of a marker on the body segment.-->
				<location> 0.00225005 -0.286 0.046</location>
				<!--Flag (true or false) specifying whether or not a marker should be kept fixed in the marker placement step.  i.e. If false, the marker is allowed to move.-->
				<fixed>true</fixed>
			</Marker>
			<Marker name="LRAD">
				<!--Body segment in the model on which the marker resides.-->
				<body>radius_l</body>
				<!--Location of a marker on the body segment.-->
				<location> -0.00218555 -0.23256 -0.0449975</location>
				<!--Flag (true or false) specifying whether or not a marker should be kept fixed in the marker placement step.  i.e. If false, the marker is allowed to move.-->
				<fixed>true</fixed>
			</Marker>
			<Marker name="LUL">
				<!--Body segment in the model on which the marker resides.-->
				<body>ulna_l</body>
				<!--Location of a marker on the body segment.-->
				<location> -0.0294326 -0.241593 -0.00596175</location>
				<!--Flag (true or false) specifying whether or not a marker should be kept fixed in the marker placement step.  i.e. If false, the marker is allowed to move.-->
				<fixed>true</fixed>
			</Marker>
			<Marker name="LRFIN">
				<!--Body segment in the model on which the marker resides.-->
				<body>hand_l</body>
				<!--Location of a marker on the body segment.-->
				<location> -0.012988 -0.075111 -0.008988</location>
				<!--Flag (true or false) specifying whether or not a marker should be kept fixed in the marker placement step.  i.e. If false, the marker is allowed to move.-->
				<fixed>true</fixed>
			</Marker>
			<Marker name="RSHO">
				<!--Body segment in the model on which the marker resides.-->
				<body>torso</body>
				<!--Location of a marker on the body segment.-->
				<location> -0.00137866 0.420924 0.148274</location>
				<!--Flag (true or false) specifying whether or not a marker should be kept fixed in the marker placement step.  i.e. If false, the marker is allowed to move.-->
				<fixed>true</fixed>
			</Marker>
			<Marker name="RUPA1">
				<!--Body segment in the model on which the marker resides.-->
				<body>humerus_r</body>
				<!--Location of a marker on the body segment.-->
				<location> -0.00113392 -0.15151 0.0191497</location>
				<!--Flag (true or false) specifying whether or not a marker should be kept fixed in the marker placement step.  i.e. If false, the marker is allowed to move.-->
				<fixed>false</fixed>
			</Marker>
			<Marker name="RMUPA">
				<!--Body segment in the model on which the marker resides.-->
				<body>humerus_r</body>
				<!--Location of a marker on the body segment.-->
				<location> 0 -0.2 0.02</location>
				<!--Flag (true or false) specifying whether or not a marker should be kept fixed in the marker placement step.  i.e. If false, the marker is allowed to move.-->
				<fixed>false</fixed>
			</Marker>
			<Marker name="RDUPA">
				<!--Body segment in the model on which the marker resides.-->
				<body>humerus_r</body>
				<!--Location of a marker on the body segment.-->
				<location> 0.0197389 -0.17739 0.0185128</location>
				<!--Flag (true or false) specifying whether or not a marker should be kept fixed in the marker placement step.  i.e. If false, the marker is allowed to move.-->
				<fixed>false</fixed>
			</Marker>
			<Marker name="RLEP">
				<!--Body segment in the model on which the marker resides.-->
				<body>humerus_r</body>
				<!--Location of a marker on the body segment.-->
				<location> 0.015 -0.28 0.04</location>
				<!--Flag (true or false) specifying whether or not a marker should be kept fixed in the marker placement step.  i.e. If false, the marker is allowed to move.-->
				<fixed>true</fixed>
			</Marker>
			<Marker name="RMEP">
				<!--Body segment in the model on which the marker resides.-->
				<body>humerus_r</body>
				<!--Location of a marker on the body segment.-->
				<location> 0.00225 -0.286 -0.046</location>
				<!--Flag (true or false) specifying whether or not a marker should be kept fixed in the marker placement step.  i.e. If false, the marker is allowed to move.-->
				<fixed>true</fixed>
			</Marker>
			<Marker name="RRAD">
				<!--Body segment in the model on which the marker resides.-->
				<body>radius_r</body>
				<!--Location of a marker on the body segment.-->
				<location> -0.00371418 -0.230706 0.0469393</location>
				<!--Flag (true or false) specifying whether or not a marker should be kept fixed in the marker placement step.  i.e. If false, the marker is allowed to move.-->
				<fixed>true</fixed>
			</Marker>
			<Marker name="RUL">
				<!--Body segment in the model on which the marker resides.-->
				<body>ulna_r</body>
				<!--Location of a marker on the body segment.-->
				<location> -0.0287888 -0.242776 0.00788761</location>
				<!--Flag (true or false) specifying whether or not a marker should be kept fixed in the marker placement step.  i.e. If false, the marker is allowed to move.-->
				<fixed>true</fixed>
			</Marker>
			<Marker name="RUFIN">
				<!--Body segment in the model on which the marker resides.-->
				<body>hand_r</body>
				<!--Location of a marker on the body segment.-->
				<location> -0.0100686 -0.0818203 0.0122632</location>
				<!--Flag (true or false) specifying whether or not a marker should be kept fixed in the marker placement step.  i.e. If false, the marker is allowed to move.-->
				<fixed>true</fixed>
			</Marker>
			<Marker name="LASI">
				<!--Body segment in the model on which the marker resides.-->
				<body>pelvis</body>
				<!--Location of a marker on the body segment.-->
				<location> 0.0154487 0.010716 -0.128922</location>
				<!--Flag (true or false) specifying whether or not a marker should be kept fixed in the marker placement step.  i.e. If false, the marker is allowed to move.-->
				<fixed>true</fixed>
			</Marker>
			<Marker name="RASI">
				<!--Body segment in the model on which the marker resides.-->
				<body>pelvis</body>
				<!--Location of a marker on the body segment.-->
				<location> 0.0172817 0.00931 0.129081</location>
				<!--Flag (true or false) specifying whether or not a marker should be kept fixed in the marker placement step.  i.e. If false, the marker is allowed to move.-->
				<fixed>true</fixed>
			</Marker>
			<Marker name="USACR">
				<!--Body segment in the model on which the marker resides.-->
				<body>pelvis</body>
				<!--Location of a marker on the body segment.-->
				<location> -0.146279 0.0249 0</location>
				<!--Flag (true or false) specifying whether or not a marker should be kept fixed in the marker placement step.  i.e. If false, the marker is allowed to move.-->
				<fixed>true</fixed>
			</Marker>
			<Marker name="LSACR">
				<!--Body segment in the model on which the marker resides.-->
				<body>pelvis</body>
				<!--Location of a marker on the body segment.-->
				<location> -0.155757 0 -0.0202784</location>
				<!--Flag (true or false) specifying whether or not a marker should be kept fixed in the marker placement step.  i.e. If false, the marker is allowed to move.-->
				<fixed>true</fixed>
			</Marker>
			<Marker name="RSACR">
				<!--Body segment in the model on which the marker resides.-->
				<body>pelvis</body>
				<!--Location of a marker on the body segment.-->
				<location> -0.151824 0 0.0202784</location>
				<!--Flag (true or false) specifying whether or not a marker should be kept fixed in the marker placement step.  i.e. If false, the marker is allowed to move.-->
				<fixed>true</fixed>
			</Marker>
			<Marker name="LHJC">
				<!--Body segment in the model on which the marker resides.-->
				<body>femur_l</body>
				<!--Location of a marker on the body segment.-->
				<location> 0 0 0</location>
				<!--Flag (true or false) specifying whether or not a marker should be kept fixed in the marker placement step.  i.e. If false, the marker is allowed to move.-->
				<fixed>true</fixed>
			</Marker>
			<Marker name="LTHI1">
				<!--Body segment in the model on which the marker resides.-->
				<body>femur_l</body>
				<!--Location of a marker on the body segment.-->
				<location> 0.0365854 -0.230779 -0.0516748</location>
				<!--Flag (true or false) specifying whether or not a marker should be kept fixed in the marker placement step.  i.e. If false, the marker is allowed to move.-->
				<fixed>false</fixed>
			</Marker>
			<Marker name="LTHI2">
				<!--Body segment in the model on which the marker resides.-->
				<body>femur_l</body>
				<!--Location of a marker on the body segment.-->
				<location> 0.0320454 -0.315382 -0.0408489</location>
				<!--Flag (true or false) specifying whether or not a marker should be kept fixed in the marker placement step.  i.e. If false, the marker is allowed to move.-->
				<fixed>false</fixed>
			</Marker>
			<Marker name="LTHI3">
				<!--Body segment in the model on which the marker resides.-->
				<body>femur_l</body>
				<!--Location of a marker on the body segment.-->
				<location> 0.0383327 -0.275807 -0.0381844</location>
				<!--Flag (true or false) specifying whether or not a marker should be kept fixed in the marker placement step.  i.e. If false, the marker is allowed to move.-->
				<fixed>false</fixed>
			</Marker>
			<Marker name="LTHI4">
				<!--Body segment in the model on which the marker resides.-->
				<body>femur_l</body>
				<!--Location of a marker on the body segment.-->
				<location> 0.0533341 -0.273209 -0.0115174</location>
				<!--Flag (true or false) specifying whether or not a marker should be kept fixed in the marker placement step.  i.e. If false, the marker is allowed to move.-->
				<fixed>false</fixed>
			</Marker>
			<Marker name="LLFC">
				<!--Body segment in the model on which the marker resides.-->
				<body>femur_l</body>
				<!--Location of a marker on the body segment.-->
				<location> -3.16575e-005 -0.408872 -0.0471372</location>
				<!--Flag (true or false) specifying whether or not a marker should be kept fixed in the marker placement step.  i.e. If false, the marker is allowed to move.-->
				<fixed>true</fixed>
			</Marker>
			<Marker name="LMFC">
				<!--Body segment in the model on which the marker resides.-->
				<body>femur_l</body>
				<!--Location of a marker on the body segment.-->
				<location> 0 -0.404 0.05</location>
				<!--Flag (true or false) specifying whether or not a marker should be kept fixed in the marker placement step.  i.e. If false, the marker is allowed to move.-->
				<fixed>true</fixed>
			</Marker>
			<Marker name="LKJC">
				<!--Body segment in the model on which the marker resides.-->
				<body>tibia_l</body>
				<!--Location of a marker on the body segment.-->
				<location> 0.001731 -0.002389 0.008452</location>
				<!--Flag (true or false) specifying whether or not a marker should be kept fixed in the marker placement step.  i.e. If false, the marker is allowed to move.-->
				<fixed>true</fixed>
			</Marker>
			<Marker name="LTIB1">
				<!--Body segment in the model on which the marker resides.-->
				<body>tibia_l</body>
				<!--Location of a marker on the body segment.-->
				<location> 0.0368692 -0.149095 0.00633472</location>
				<!--Flag (true or false) specifying whether or not a marker should be kept fixed in the marker placement step.  i.e. If false, the marker is allowed to move.-->
				<fixed>false</fixed>
			</Marker>
			<Marker name="LTIB2">
				<!--Body segment in the model on which the marker resides.-->
				<body>tibia_l</body>
				<!--Location of a marker on the body segment.-->
				<location> 0.0378625 -0.20293 0.00607872</location>
				<!--Flag (true or false) specifying whether or not a marker should be kept fixed in the marker placement step.  i.e. If false, the marker is allowed to move.-->
				<fixed>false</fixed>
			</Marker>
			<Marker name="LTIB3">
				<!--Body segment in the model on which the marker resides.-->
				<body>tibia_l</body>
				<!--Location of a marker on the body segment.-->
				<location> 0.0333672 -0.204224 -0.0217876</location>
				<!--Flag (true or false) specifying whether or not a marker should be kept fixed in the marker placement step.  i.e. If false, the marker is allowed to move.-->
				<fixed>false</fixed>
			</Marker>
			<Marker name="LTIB4">
				<!--Body segment in the model on which the marker resides.-->
				<body>tibia_l</body>
				<!--Location of a marker on the body segment.-->
				<location> 0.0263853 -0.248053 0.00708025</location>
				<!--Flag (true or false) specifying whether or not a marker should be kept fixed in the marker placement step.  i.e. If false, the marker is allowed to move.-->
				<fixed>false</fixed>
			</Marker>
			<Marker name="LLMAL">
				<!--Body segment in the model on which the marker resides.-->
				<body>tibia_l</body>
				<!--Location of a marker on the body segment.-->
				<location> -0.0115346 -0.383953 -0.0472023</location>
				<!--Flag (true or false) specifying whether or not a marker should be kept fixed in the marker placement step.  i.e. If false, the marker is allowed to move.-->
				<fixed>true</fixed>
			</Marker>
			<Marker name="LMMAL">
				<!--Body segment in the model on which the marker resides.-->
				<body>tibia_l</body>
				<!--Location of a marker on the body segment.-->
				<location> 0.00388774 -0.370945 0.0390254</location>
				<!--Flag (true or false) specifying whether or not a marker should be kept fixed in the marker placement step.  i.e. If false, the marker is allowed to move.-->
				<fixed>true</fixed>
			</Marker>
			<Marker name="LAJC">
				<!--Body segment in the model on which the marker resides.-->
				<body>talus_l</body>
				<!--Location of a marker on the body segment.-->
				<location> 0 0 0</location>
				<!--Flag (true or false) specifying whether or not a marker should be kept fixed in the marker placement step.  i.e. If false, the marker is allowed to move.-->
				<fixed>true</fixed>
			</Marker>
			<Marker name="LHEE">
				<!--Body segment in the model on which the marker resides.-->
				<body>calcn_l</body>
				<!--Location of a marker on the body segment.-->
				<location> -0.0164675 0.0208231 0.00631294</location>
				<!--Flag (true or false) specifying whether or not a marker should be kept fixed in the marker placement step.  i.e. If false, the marker is allowed to move.-->
				<fixed>true</fixed>
			</Marker>
			<Marker name="LMT1">
				<!--Body segment in the model on which the marker resides.-->
				<body>calcn_l</body>
				<!--Location of a marker on the body segment.-->
				<location> 0.197475 0.0146808 0.0262583</location>
				<!--Flag (true or false) specifying whether or not a marker should be kept fixed in the marker placement step.  i.e. If false, the marker is allowed to move.-->
				<fixed>true</fixed>
			</Marker>
			<Marker name="LMT2">
				<!--Body segment in the model on which the marker resides.-->
				<body>calcn_l</body>
				<!--Location of a marker on the body segment.-->
				<location> 0.182849 0.0120803 -0.0149008</location>
				<!--Flag (true or false) specifying whether or not a marker should be kept fixed in the marker placement step.  i.e. If false, the marker is allowed to move.-->
				<fixed>true</fixed>
			</Marker>
			<Marker name="LMT5">
				<!--Body segment in the model on which the marker resides.-->
				<body>calcn_l</body>
				<!--Location of a marker on the body segment.-->
				<location> 0.149009 0.0140902 -0.0538267</location>
				<!--Flag (true or false) specifying whether or not a marker should be kept fixed in the marker placement step.  i.e. If false, the marker is allowed to move.-->
				<fixed>true</fixed>
			</Marker>
			<Marker name="RHJC">
				<!--Body segment in the model on which the marker resides.-->
				<body>pelvis</body>
				<!--Location of a marker on the body segment.-->
				<location> -0.056276 -0.07849 0.07726</location>
				<!--Flag (true or false) specifying whether or not a marker should be kept fixed in the marker placement step.  i.e. If false, the marker is allowed to move.-->
				<fixed>true</fixed>
			</Marker>
			<Marker name="RTHI">
				<!--Body segment in the model on which the marker resides.-->
				<body>femur_r</body>
				<!--Location of a marker on the body segment.-->
				<location> 0.0271379 -0.201617 0.0491218</location>
				<!--Flag (true or false) specifying whether or not a marker should be kept fixed in the marker placement step.  i.e. If false, the marker is allowed to move.-->
				<fixed>false</fixed>
			</Marker>
			<Marker name="RTHI2">
				<!--Body segment in the model on which the marker resides.-->
				<body>femur_r</body>
				<!--Location of a marker on the body segment.-->
				<location> 0.0507586 -0.234574 0.039248</location>
				<!--Flag (true or false) specifying whether or not a marker should be kept fixed in the marker placement step.  i.e. If false, the marker is allowed to move.-->
				<fixed>false</fixed>
			</Marker>
			<Marker name="RTHI3">
				<!--Body segment in the model on which the marker resides.-->
				<body>femur_r</body>
				<!--Location of a marker on the body segment.-->
				<location> 0.0687571 -0.231384 0.0102367</location>
				<!--Flag (true or false) specifying whether or not a marker should be kept fixed in the marker placement step.  i.e. If false, the marker is allowed to move.-->
				<fixed>false</fixed>
			</Marker>
			<Marker name="RTHI4">
				<!--Body segment in the model on which the marker resides.-->
				<body>femur_r</body>
				<!--Location of a marker on the body segment.-->
				<location> 0.0315926 -0.273869 0.0416775</location>
				<!--Flag (true or false) specifying whether or not a marker should be kept fixed in the marker placement step.  i.e. If false, the marker is allowed to move.-->
				<fixed>false</fixed>
			</Marker>
			<Marker name="RLFC">
				<!--Body segment in the model on which the marker resides.-->
				<body>femur_r</body>
				<!--Location of a marker on the body segment.-->
				<location> 0 -0.404 0.05</location>
				<!--Flag (true or false) specifying whether or not a marker should be kept fixed in the marker placement step.  i.e. If false, the marker is allowed to move.-->
				<fixed>true</fixed>
			</Marker>
			<Marker name="RMFC">
				<!--Body segment in the model on which the marker resides.-->
				<body>femur_r</body>
				<!--Location of a marker on the body segment.-->
				<location> 0 -0.404 -0.05</location>
				<!--Flag (true or false) specifying whether or not a marker should be kept fixed in the marker placement step.  i.e. If false, the marker is allowed to move.-->
				<fixed>true</fixed>
			</Marker>
			<Marker name="RKJC">
				<!--Body segment in the model on which the marker resides.-->
				<body>tibia_r</body>
				<!--Location of a marker on the body segment.-->
				<location> 0.001731 -0.002389 -0.008452</location>
				<!--Flag (true or false) specifying whether or not a marker should be kept fixed in the marker placement step.  i.e. If false, the marker is allowed to move.-->
				<fixed>true</fixed>
			</Marker>
			<Marker name="RTIB1">
				<!--Body segment in the model on which the marker resides.-->
				<body>tibia_r</body>
				<!--Location of a marker on the body segment.-->
				<location> 0.042085 -0.184868 -0.00589999</location>
				<!--Flag (true or false) specifying whether or not a marker should be kept fixed in the marker placement step.  i.e. If false, the marker is allowed to move.-->
				<fixed>false</fixed>
			</Marker>
			<Marker name="RTIB2">
				<!--Body segment in the model on which the marker resides.-->
				<body>tibia_r</body>
				<!--Location of a marker on the body segment.-->
				<location> 0.0369643 -0.230107 -0.00391699</location>
				<!--Flag (true or false) specifying whether or not a marker should be kept fixed in the marker placement step.  i.e. If false, the marker is allowed to move.-->
				<fixed>false</fixed>
			</Marker>
			<Marker name="RTIB3">
				<!--Body segment in the model on which the marker resides.-->
				<body>tibia_r</body>
				<!--Location of a marker on the body segment.-->
				<location> 0.0253163 -0.234812 0.026079</location>
				<!--Flag (true or false) specifying whether or not a marker should be kept fixed in the marker placement step.  i.e. If false, the marker is allowed to move.-->
				<fixed>false</fixed>
			</Marker>
			<Marker name="RTIB4">
				<!--Body segment in the model on which the marker resides.-->
				<body>tibia_r</body>
				<!--Location of a marker on the body segment.-->
				<location> 0.0387123 -0.289217 -0.00443473</location>
				<!--Flag (true or false) specifying whether or not a marker should be kept fixed in the marker placement step.  i.e. If false, the marker is allowed to move.-->
				<fixed>false</fixed>
			</Marker>
			<Marker name="RLMAL">
				<!--Body segment in the model on which the marker resides.-->
				<body>tibia_r</body>
				<!--Location of a marker on the body segment.-->
				<location> -0.0189532 -0.389828 0.0466999</location>
				<!--Flag (true or false) specifying whether or not a marker should be kept fixed in the marker placement step.  i.e. If false, the marker is allowed to move.-->
				<fixed>true</fixed>
			</Marker>
			<Marker name="RMMAL">
				<!--Body segment in the model on which the marker resides.-->
				<body>tibia_r</body>
				<!--Location of a marker on the body segment.-->
				<location> 0.00646463 -0.373191 -0.0395495</location>
				<!--Flag (true or false) specifying whether or not a marker should be kept fixed in the marker placement step.  i.e. If false, the marker is allowed to move.-->
				<fixed>true</fixed>
			</Marker>
			<Marker name="RAJC">
				<!--Body segment in the model on which the marker resides.-->
				<body>talus_r</body>
				<!--Location of a marker on the body segment.-->
				<location> 0 0 0</location>
				<!--Flag (true or false) specifying whether or not a marker should be kept fixed in the marker placement step.  i.e. If false, the marker is allowed to move.-->
				<fixed>true</fixed>
			</Marker>
			<Marker name="RHEE">
				<!--Body segment in the model on which the marker resides.-->
				<body>calcn_r</body>
				<!--Location of a marker on the body segment.-->
				<location> -0.0181589 0.0200512 -0.00474971</location>
				<!--Flag (true or false) specifying whether or not a marker should be kept fixed in the marker placement step.  i.e. If false, the marker is allowed to move.-->
				<fixed>true</fixed>
			</Marker>
			<Marker name="RMT1">
				<!--Body segment in the model on which the marker resides.-->
				<body>calcn_r</body>
				<!--Location of a marker on the body segment.-->
				<location> 0.19668 0.0164655 -0.026274</location>
				<!--Flag (true or false) specifying whether or not a marker should be kept fixed in the marker placement step.  i.e. If false, the marker is allowed to move.-->
				<fixed>true</fixed>
			</Marker>
			<Marker name="RMT2">
				<!--Body segment in the model on which the marker resides.-->
				<body>calcn_r</body>
				<!--Location of a marker on the body segment.-->
				<location> 0.173234 0.0159901 0.00971763</location>
				<!--Flag (true or false) specifying whether or not a marker should be kept fixed in the marker placement step.  i.e. If false, the marker is allowed to move.-->
				<fixed>true</fixed>
			</Marker>
			<Marker name="RMT5">
				<!--Body segment in the model on which the marker resides.-->
				<body>calcn_r</body>
				<!--Location of a marker on the body segment.-->
				<location> 0.14084 0.0150493 0.0543693</location>
				<!--Flag (true or false) specifying whether or not a marker should be kept fixed in the marker placement step.  i.e. If false, the marker is allowed to move.-->
				<fixed>true</fixed>
			</Marker>
			<Marker name="RHHE_floor">
				<!--Body segment in the model on which the marker resides.-->
				<body>calcn_r</body>
				<!--Location of a marker on the body segment.-->
				<location> -0.0181589 0 -0.00474971</location>
				<!--Flag (true or false) specifying whether or not a marker should be kept fixed in the marker placement step.  i.e. If false, the marker is allowed to move.-->
				<fixed>false</fixed>
			</Marker>
			<Marker name="MidASIS">
				<!--Body segment in the model on which the marker resides.-->
				<body>pelvis</body>
				<!--Location of a marker on the body segment.-->
				<location> 0.0172817 0.00931 0</location>
				<!--Flag (true or false) specifying whether or not a marker should be kept fixed in the marker placement step.  i.e. If false, the marker is allowed to move.-->
				<fixed>false</fixed>
			</Marker>
			<Marker name="MidHJC">
				<!--Body segment in the model on which the marker resides.-->
				<body>pelvis</body>
				<!--Location of a marker on the body segment.-->
				<location> -0.056276 -0.07849 0</location>
				<!--Flag (true or false) specifying whether or not a marker should be kept fixed in the marker placement step.  i.e. If false, the marker is allowed to move.-->
				<fixed>false</fixed>
			</Marker>
			<Marker name="MidSACR">
				<!--Body segment in the model on which the marker resides.-->
				<body>pelvis</body>
				<!--Location of a marker on the body segment.-->
				<location> -0.151949 0 0</location>
				<!--Flag (true or false) specifying whether or not a marker should be kept fixed in the marker placement step.  i.e. If false, the marker is allowed to move.-->
				<fixed>false</fixed>
			</Marker>
			<Marker name="MidPelvis">
				<!--Body segment in the model on which the marker resides.-->
				<body>pelvis</body>
				<!--Location of a marker on the body segment.-->
				<location> -0.056276 0 0</location>
				<!--Flag (true or false) specifying whether or not a marker should be kept fixed in the marker placement step.  i.e. If false, the marker is allowed to move.-->
				<fixed>false</fixed>
			</Marker>
		</objects>
		<groups />
	</MarkerSet>
</OpenSimDocument>
